tiny_shmup.py
tiny_shmup-0.1.0.dist-info/METADATA
tiny_shmup-0.1.0.dist-info/WHEEL
tiny_shmup-0.1.0.dist-info/licenses/LICENSE
tiny_shmup-0.1.0.dist-info/RECORD
